ai_palette/__init__.py
ai_palette/app.py
ai_palette/static/css/theme.css
ai_palette/static/image/qrcode.jpg
ai_palette/static/image/web_demo.png
ai_palette/static/js/app.js
ai_palette/static/js/tailwind.js
ai_palette/static/js/theme.js
ai_palette/templates/index.html
ai_palette/templates/intro.html
ai_palette-0.1.14.dist-info/LICENSE
ai_palette-0.1.14.dist-info/METADATA
ai_palette-0.1.14.dist-info/WHEEL
ai_palette-0.1.14.dist-info/entry_points.txt
ai_palette-0.1.14.dist-info/top_level.txt
ai_palette-0.1.14.dist-info/RECORD
