Metadata-Version: 2.2
Name: ai-palette
Version: 0.1.14
Summary: A lightweight and elegant unified AI interface
Home-page: https://github.com/itshen/ai_palette
Author: Eason Tsui
Author-email: AI Palette Team <eason@miyang.ai>
Project-URL: Homepage, https://github.com/itshen/ai_palette
Project-URL: Repository, https://github.com/itshen/ai_palette.git
Classifier: Programming Language :: Python :: 3
Classifier: License :: OSI Approved :: MIT License
Classifier: Operating System :: OS Independent
Requires-Python: >=3.7
License-File: LICENSE
Requires-Dist: requests>=2.31.0
Requires-Dist: aiohttp>=3.9.1
Requires-Dist: loguru>=0.7.2
Requires-Dist: python-dotenv>=1.0.0
Requires-Dist: typing-extensions>=4.9.0
Requires-Dist: flask>=3.0.0
Dynamic: author
Dynamic: home-page
Dynamic: requires-python
